wispr/__init__.py
wispr-1.0.dist-info/DESCRIPTION.rst
wispr-1.0.dist-info/entry_points.txt
wispr-1.0.dist-info/METADATA
wispr-1.0.dist-info/metadata.json
wispr-1.0.dist-info/RECORD
wispr-1.0.dist-info/top_level.txt
wispr-1.0.dist-info/WHEEL
