Metadata-Version: 2.0
Name: wispr
Version: 1.0
Summary: WISPr command line client
Home-page: https://github.com/wichert/wispr
Author: Wichert Akkerman
Author-email: wichert@wiggy.net
License: BSD
Keywords: wispr wifi hotspot
Platform: UNKNOWN
Classifier: Environment :: Console
Classifier: License :: DFSG approved
Classifier: License :: OSI Approved :: BSD License
Classifier: Operating System :: OS Independent
Classifier: Intended Audience :: End Users/Desktop
Requires-Dist: requests
